{
    "os": "Linux-5.15.0-60-generic-x86_64-with-glibc2.35",
    "python": "3.10.6",
    "heartbeatAt": "2023-02-23T00:36:28.126981",
    "startedAt": "2023-02-23T00:36:27.629267",
    "docker": null,
    "cuda": null,
    "args": null,
    "state": "running",
    "program": "<python with no main file>",
    "git": {
        "remote": "https://github.com/xiaosuhu/RSNA2022_Kaggle.git",
        "commit": "54c63da330474edf25c7a63ffa95b7d33785b14b"
    },
    "email": "xiaosuhu@outlook.com",
    "root": "/home/frank/Documents/RSNA_MAMMO_1024x512/Code",
    "host": "frank-OMEN-30L",
    "username": "frank",
    "executable": "/bin/python3",
    "cpu_count": 6,
    "cpu_count_logical": 12,
    "cpu_freq": {
        "current": 2.9937500000000004,
        "min": 2200.0,
        "max": 3700.0
    },
    "cpu_freq_per_core": [
        {
            "current": 2.2,
            "min": 2200.0,
            "max": 3700.0
        },
        {
            "current": 2.2,
            "min": 2200.0,
            "max": 3700.0
        },
        {
            "current": 2.2,
            "min": 2200.0,
            "max": 3700.0
        },
        {
            "current": 3.7,
            "min": 2200.0,
            "max": 3700.0
        },
        {
            "current": 2.2,
            "min": 2200.0,
            "max": 3700.0
        },
        {
            "current": 3.7,
            "min": 2200.0,
            "max": 3700.0
        },
        {
            "current": 3.7,
            "min": 2200.0,
            "max": 3700.0
        },
        {
            "current": 3.7,
            "min": 2200.0,
            "max": 3700.0
        },
        {
            "current": 2.8,
            "min": 2200.0,
            "max": 3700.0
        },
        {
            "current": 3.625,
            "min": 2200.0,
            "max": 3700.0
        },
        {
            "current": 3.7,
            "min": 2200.0,
            "max": 3700.0
        },
        {
            "current": 2.2,
            "min": 2200.0,
            "max": 3700.0
        }
    ],
    "disk": {
        "total": 232.85187911987305,
        "used": 121.77991104125977
    },
    "gpu": "NVIDIA GeForce RTX 3080",
    "gpu_count": 1,
    "gpu_devices": [
        {
            "name": "NVIDIA GeForce RTX 3080",
            "memory_total": 10737418240
        }
    ],
    "memory": {
        "total": 31.258647918701172
    }
}
